{
  "lastUpdated": "2026-04-06T09:02:21.940477+08:00",
  "config": {
    "category": "global",
    "autoUpdate": true
  },
  "competitors": [
    {
      "name": "github.com/topics/ai-tools",
      "domain": "github.com/topics/ai-tools",
      "url": "https://github.com/topics/ai-tools",
      "description": "structured-source",
      "monthlyVisits": 0,
      "hasTraffic": false,
      "id": "github-com-topics-ai-tools",
      "tier": "T4",
      "trafficTrend": [],
      "type": "global",
      "features": [
        "AI",
        "global"
      ]
    },
    {
      "name": "www.producthunt.com/topics/artificial-intelligence",
      "domain": "producthunt.com/topics/artificial-intelligence",
      "url": "https://www.producthunt.com/topics/artificial-intelligence",
      "description": "structured-source",
      "monthlyVisits": 0,
      "hasTraffic": false,
      "id": "producthunt-com-topics-artific",
      "tier": "T4",
      "trafficTrend": [],
      "type": "global",
      "features": [
        "AI",
        "global"
      ]
    },
    {
      "name": "alternativeto.net/category/ai-machine-learning",
      "domain": "alternativeto.net/category/ai-machine-learning",
      "url": "https://alternativeto.net/category/ai-machine-learning",
      "description": "structured-source",
      "monthlyVisits": 0,
      "hasTraffic": false,
      "id": "alternativeto-net-category-ai-",
      "tier": "T4",
      "trafficTrend": [],
      "type": "global",
      "features": [
        "AI",
        "global"
      ]
    },
    {
      "name": "www.futuretools.io",
      "domain": "futuretools.io",
      "url": "https://www.futuretools.io",
      "description": "structured-source",
      "monthlyVisits": 0,
      "hasTraffic": false,
      "id": "futuretools-io",
      "tier": "T4",
      "trafficTrend": [],
      "type": "global",
      "features": [
        "AI",
        "global"
      ]
    },
    {
      "name": "www.futurepedia.io",
      "domain": "futurepedia.io",
      "url": "https://www.futurepedia.io",
      "description": "structured-source",
      "monthlyVisits": 0,
      "hasTraffic": false,
      "id": "futurepedia-io",
      "tier": "T4",
      "trafficTrend": [],
      "type": "global",
      "features": [
        "AI",
        "global"
      ]
    },
    {
      "name": "Theresanaiforthat",
      "domain": "theresanaiforthat.com",
      "url": "https://theresanaiforthat.com",
      "description": "",
      "monthlyVisits": 0,
      "hasTraffic": false,
      "id": "theresanaiforthat-com",
      "tier": "T4",
      "trafficTrend": [],
      "type": "global",
      "features": [
        "AI",
        "global"
      ]
    },
    {
      "name": "Toolify",
      "domain": "toolify.ai",
      "url": "https://toolify.ai",
      "description": "",
      "monthlyVisits": 0,
      "hasTraffic": false,
      "id": "toolify-ai",
      "tier": "T4",
      "trafficTrend": [],
      "type": "global",
      "features": [
        "AI",
        "global"
      ]
    },
    {
      "name": "Aitools",
      "domain": "aitools.fyi",
      "url": "https://aitools.fyi",
      "description": "",
      "monthlyVisits": 0,
      "hasTraffic": false,
      "id": "aitools-fyi",
      "tier": "T4",
      "trafficTrend": [],
      "type": "global",
      "features": [
        "AI",
        "global"
      ]
    },
    {
      "name": "Topai",
      "domain": "topai.tools",
      "url": "https://topai.tools",
      "description": "",
      "monthlyVisits": 0,
      "hasTraffic": false,
      "id": "topai-tools",
      "tier": "T4",
      "trafficTrend": [],
      "type": "global",
      "features": [
        "AI",
        "global"
      ]
    },
    {
      "name": "Aitoolsdirectory",
      "domain": "aitoolsdirectory.com",
      "url": "https://aitoolsdirectory.com",
      "description": "",
      "monthlyVisits": 0,
      "hasTraffic": false,
      "id": "aitoolsdirectory-com",
      "tier": "T4",
      "trafficTrend": [],
      "type": "global",
      "features": [
        "AI",
        "global"
      ]
    },
    {
      "name": "G2",
      "domain": "g2.com/categories/ai-writing-assistant",
      "url": "https://g2.com/categories/ai-writing-assistant",
      "description": "",
      "monthlyVisits": 0,
      "hasTraffic": false,
      "id": "g2-com-categories-ai-writing-a",
      "tier": "T4",
      "trafficTrend": [],
      "type": "global",
      "features": [
        "AI",
        "global"
      ]
    }
  ],
  "insights": [
    {
      "title": "🏆 头部集中",
      "content": "T1 级别 0 个，占据主要流量",
      "color": "blue"
    },
    {
      "title": "📈 总流量",
      "content": "有流量网站月访问总量 0.0M",
      "color": "green"
    },
    {
      "title": "🧩 长尾补充",
      "content": "另收录 11 个暂无流量数据的网站，默认靠后展示",
      "color": "purple"
    }
  ],
  "metrics": {
    "totalSites": 11,
    "totalMonthlyVisits": 0
  }
}